{
  "word": "nö",
  "pos": "particle",
  "etymology_number": null,
  "senses": [
    {
      "gloss": "nein",
      "gloss_en": "no",
      "tags": [
        "colloquial"
      ],
      "example_ids": [
        "a629d04c7b"
      ],
      "synonyms": [],
      "antonyms": [],
      "gloss_en_model": "lm-studio/sauerkraut"
    }
  ],
  "sounds": [
    {
      "ipa": "[nøː]",
      "tags": []
    }
  ],
  "_meta": {
    "source_hash": "7604eb5c384e1626",
    "generated_at": "2026-03-09"
  },
  "zipf": 3.21
}