{
  "word": "aus sich heraus",
  "pos": "phrase",
  "etymology_number": null,
  "senses": [
    {
      "gloss": "ohne direkte Aufforderung, aus eigenem Antrieb",
      "gloss_en": null,
      "tags": [],
      "example_ids": [
        "a7102aad66"
      ],
      "synonyms": [],
      "antonyms": []
    }
  ],
  "sounds": [
    {
      "ipa": "[…]",
      "tags": []
    }
  ],
  "_antonyms": [
    "gezwungen",
    "unfreiwillig"
  ],
  "_synonyms": [
    "aus freien Stücken",
    "freiwillig",
    "unaufgefordert",
    "von sich aus"
  ],
  "_meta": {
    "source_hash": "b5916482d3f5cd93",
    "generated_at": "2026-03-06"
  }
}