{
  "word": "die Ohren steif halten",
  "pos": "phrase",
  "etymology_number": null,
  "senses": [
    {
      "gloss": "sich tapfer halten, aufmerksam sein",
      "gloss_en": null,
      "tags": [],
      "example_ids": [
        "f5222402fe",
        "6cc2d20308",
        "9ff3e6b6f8"
      ],
      "synonyms": [],
      "antonyms": []
    }
  ],
  "sounds": [
    {
      "ipa": "[diː ˈoːʁən ˈʃtaɪ̯f ˈhaltn̩]",
      "tags": []
    }
  ],
  "phrase_type": "idiom",
  "_antonyms": [
    "die Ohren hängen lassen"
  ],
  "_meta": {
    "source_hash": "a800c5201fccd019",
    "generated_at": "2026-03-09"
  }
}
