{
  "word": "die Fäden in der Hand haben",
  "pos": "phrase",
  "etymology_number": null,
  "senses": [
    {
      "gloss": "die Kontrolle haben, das Sagen haben",
      "gloss_en": null,
      "tags": [],
      "example_ids": [
        "7ddd19e5e8"
      ],
      "synonyms": [],
      "antonyms": []
    }
  ],
  "sounds": [
    {
      "ipa": "[…]",
      "tags": []
    }
  ],
  "_synonyms": [
    "leiten",
    "lenken",
    "steuern",
    "das Heft in der Hand halten"
  ],
  "_meta": {
    "source_hash": "3dbf67c957478b67",
    "generated_at": "2026-03-06"
  }
}