{
  "word": "dumm fickt gut",
  "pos": "phrase",
  "etymology_number": null,
  "senses": [
    {
      "gloss": "eine niedrige Intelligenz führt zu einem besseren Sexerlebnis",
      "gloss_en": null,
      "tags": [
        "colloquial",
        "derogatory"
      ],
      "example_ids": [
        "665a5f44b3",
        "da94b0cace",
        "4df6d940c2",
        "4967246e67",
        "715bc90cf8"
      ],
      "synonyms": [],
      "antonyms": []
    }
  ],
  "sounds": [
    {
      "ipa": "[…]",
      "tags": []
    }
  ],
  "_meta": {
    "source_hash": "00b76cf2aeffbf82",
    "generated_at": "2026-03-01"
  }
}