{
  "word": "etwas mit Kusshand nehmen",
  "pos": "phrase",
  "etymology_number": null,
  "senses": [
    {
      "gloss": "etwas gern entgegennehmen; sich über eine Gabe freuen",
      "gloss_en": "take with pleasure",
      "tags": [],
      "example_ids": [
        "2d7af6f494"
      ],
      "synonyms": [],
      "antonyms": []
    }
  ],
  "sounds": [
    {
      "ipa": "[…]",
      "tags": []
    }
  ],
  "phrase_type": "idiom",
  "_meta": {
    "source_hash": "80f8f9e08589d290",
    "generated_at": "2026-03-09"
  }
}
