{
  "word": "forensische Psychiatrie",
  "pos": "phrase",
  "etymology_number": null,
  "senses": [
    {
      "gloss": "Teilgebiet der Psychiatrie, das sich mit der Begutachtung, der Unterbringung und der Behandlung von psychisch kranken Straftätern befasst",
      "gloss_en": null,
      "tags": [],
      "example_ids": [
        "f0dcfcf747"
      ],
      "synonyms": [],
      "antonyms": []
    },
    {
      "gloss": "psychiatrische Anstalt, in der psychisch kranke Straftäter untergebracht sind",
      "gloss_en": null,
      "tags": [
        "colloquial"
      ],
      "example_ids": [
        "f1a3fdf841"
      ],
      "synonyms": [],
      "antonyms": []
    }
  ],
  "sounds": [
    {
      "ipa": "[foˈʁɛnzɪʃə psyçi̯aˈtʁiː]",
      "tags": []
    }
  ],
  "_meta": {
    "source_hash": "6695cfcbb496120c",
    "generated_at": "2026-03-01"
  }
}