{
  "word": "Freudscher Versprecher",
  "pos": "phrase",
  "etymology_number": null,
  "senses": [
    {
      "gloss": "Versprecher, bei dem der Hörer – und manchmal auch der Sprecher selbst – annimmt, dass der Sprecher ungewollt etwas von sich preisgegeben habe",
      "gloss_en": "Freudian slip",
      "tags": [],
      "example_ids": [
        "0976ab3089",
        "3c61a8abfd"
      ],
      "synonyms": [],
      "antonyms": [],
      "gloss_en_model": "lm-studio/sauerkraut"
    }
  ],
  "sounds": [
    {
      "ipa": "[ˌfʁɔɪ̯tʃɐ fɛɐ̯ˈʃpʁɛçɐ]",
      "tags": []
    }
  ],
  "phrase_type": "collocation",
  "_meta": {
    "source_hash": "ff054cf87c822422",
    "generated_at": "2026-03-09"
  }
}
