{
  "word": "Gras über etwas wachsen lassen",
  "pos": "phrase",
  "etymology_number": null,
  "senses": [
    {
      "gloss": "etwas in Vergessenheit geraten lassen",
      "gloss_en": null,
      "tags": [],
      "example_ids": [
        "7428360d20"
      ],
      "synonyms": [],
      "antonyms": []
    }
  ],
  "sounds": [
    {
      "ipa": "[ˈɡʁaːs yːbɐ ɛtvas ˈvaksn̩ ˈlasn̩]",
      "tags": []
    }
  ],
  "_meta": {
    "source_hash": "b654d1c27e5914b8",
    "generated_at": "2026-03-01"
  }
}