{
  "word": "in den Arsch kriechen",
  "pos": "phrase",
  "etymology_number": null,
  "senses": [
    {
      "gloss": "sich Menschen mit einem übertrieben freundlichen Wohlwollen unterwerfen, um sich eigene Vorteile zu verschaffen oder zu sichern; vor keiner Erniedrigung zurückschrecken",
      "gloss_en": null,
      "tags": [],
      "example_ids": [
        "64e4403d9f"
      ],
      "synonyms": [],
      "antonyms": []
    }
  ],
  "sounds": [
    {
      "ipa": "[ɪn deːn ˈaʁʃ ˈkʁiːçn̩]",
      "tags": []
    }
  ],
  "phrase_type": "idiom",
  "_derived": [
    "Arschkriecher",
    "Arschkriecherei"
  ],
  "_synonyms": [
    "einschleimen",
    "einschmeicheln",
    "jemandem die Füße küssen"
  ],
  "_meta": {
    "source_hash": "75194e4db6f55848",
    "generated_at": "2026-03-09"
  }
}
