{
  "word": "jemandem bleibt die Sprache weg",
  "pos": "phrase",
  "etymology_number": null,
  "senses": [
    {
      "gloss": "etwas erstaunt, überrascht einen so sehr, dass man sprachlos ist.",
      "gloss_en": "speechless",
      "tags": [],
      "example_ids": [
        "55e8eb6ad0"
      ],
      "synonyms": [],
      "antonyms": []
    }
  ],
  "sounds": [
    {
      "ipa": "[ˈjeːmandm̩ ˌblaɪ̯pt diː ˈʃpʁaːxə ˌvɛk]",
      "tags": []
    }
  ],
  "phrase_type": "idiom",
  "_synonyms": [
    "jemandem verschlägt es die Sprache",
    "jemandem bleibt die Spucke weg"
  ],
  "_meta": {
    "source_hash": "f8449622e7fea3c7",
    "generated_at": "2026-03-09"
  }
}
