{
  "word": "jemanden unter seine Fittiche nehmen",
  "pos": "phrase",
  "etymology_number": null,
  "senses": [
    {
      "gloss": "sich jemandes annehmen, indem man der betreffenden Person Fürsorge, Obhut, Schutz oder sonstigen (fördernden) Beistand zuteilwerden lässt",
      "gloss_en": null,
      "tags": [
        "colloquial",
        "jocular"
      ],
      "example_ids": [
        "5a884d06f3",
        "d23f671b5d",
        "402fd4404a"
      ],
      "synonyms": [],
      "antonyms": []
    }
  ],
  "sounds": [
    {
      "ipa": "[ˌjeːmandn̩ ˌʔʊntɐ ˌzaɪ̯nə ˈfɪtɪçə ˌneːmən]",
      "tags": []
    }
  ],
  "_meta": {
    "source_hash": "2c8093420648e69e",
    "generated_at": "2026-03-01"
  }
}