{
  "word": "kaputt treten",
  "pos": "phrase",
  "etymology_number": null,
  "senses": [
    {
      "gloss": "mit einem Tritt, durch (andauerndes) (Darauf-)Treten zerstören",
      "gloss_en": null,
      "tags": [
        "colloquial",
        "transitive"
      ],
      "example_ids": [
        "559b556a35"
      ],
      "synonyms": [],
      "antonyms": []
    }
  ],
  "sounds": [
    {
      "ipa": "[kaˈpʊtˌtʁeːtn̩]",
      "tags": []
    }
  ],
  "_derived": [
    "kaputt getreten",
    "Kaputttreten",
    "kaputt tretend"
  ],
  "_synonyms": [
    "zertreten"
  ],
  "_meta": {
    "source_hash": "0d27745579aaf4b5",
    "generated_at": "2026-03-06"
  }
}