{
  "word": "mit bloßem Auge",
  "pos": "phrase",
  "etymology_number": null,
  "senses": [
    {
      "gloss": "ohne optische Hilfsmittel wie Brille, Fernglas, Lupe, Mikroskop, Teleskop oder dergleichen",
      "gloss_en": "with the naked eye",
      "tags": [],
      "example_ids": [
        "d96d29db4a",
        "7647a532f3",
        "53f5a02368",
        "f58099bfd7",
        "6b2e3f0af4",
        "da605afee6",
        "63e90bb51d",
        "c7ce00d58c",
        "79a0e9a322",
        "395f88140b"
      ],
      "synonyms": [],
      "antonyms": [],
      "gloss_en_model": "lm-studio/sauerkraut"
    }
  ],
  "sounds": [
    {
      "ipa": "[ˌmɪt bloːsm̩ ˈʔaʊ̯ɡə]",
      "tags": []
    }
  ],
  "phrase_type": "idiom",
  "_synonyms": [
    "mit nacktem Auge",
    "mit unbewaffnetem Auge",
    "mit freiem Auge",
    "von blossem Auge",
    "von Auge"
  ],
  "_meta": {
    "source_hash": "aad3b5af82f28027",
    "generated_at": "2026-03-09"
  }
}