{
  "word": "Nerven wie Drahtseile haben",
  "pos": "phrase",
  "etymology_number": null,
  "senses": [
    {
      "gloss": "psychischen Belastungen standhalten können",
      "gloss_en": "have nerves of steel",
      "tags": [
        "colloquial"
      ],
      "example_ids": [
        "bd2ecb5827"
      ],
      "synonyms": [],
      "antonyms": [],
      "gloss_en_model": "lm-studio/sauerkraut"
    }
  ],
  "sounds": [
    {
      "ipa": "[…]",
      "tags": []
    }
  ],
  "phrase_type": "idiom",
  "_meta": {
    "source_hash": "749d89fe40e04e41",
    "generated_at": "2026-03-09"
  }
}
