{
  "word": "nicht alle Pfeile im Köcher haben",
  "pos": "phrase",
  "etymology_number": null,
  "senses": [
    {
      "gloss": "leicht verrückt sein, geistig nicht ganz zurechnungsfähig sein",
      "gloss_en": "not all there",
      "tags": [
        "colloquial"
      ],
      "example_ids": [
        "ff32ab72a7"
      ],
      "synonyms": [],
      "antonyms": [],
      "gloss_en_model": "lm-studio/sauerkraut"
    }
  ],
  "sounds": [
    {
      "ipa": "[…]",
      "tags": []
    }
  ],
  "phrase_type": "idiom",
  "_synonyms": [
    "nicht alle Latten am Zaun haben",
    "nicht alle Tassen im Schrank haben"
  ],
  "_meta": {
    "source_hash": "8acd8fe19c161ac0",
    "generated_at": "2026-03-09"
  }
}
