{
  "word": "nicht die Bohne",
  "pos": "phrase",
  "etymology_number": null,
  "senses": [
    {
      "gloss": "gar nicht(s), überhaupt nicht(s), keineswegs",
      "gloss_en": "not at all",
      "tags": [
        "colloquial"
      ],
      "example_ids": [
        "fcc9d797d2",
        "100f97d297",
        "10d696c6ba"
      ],
      "synonyms": [],
      "antonyms": [],
      "gloss_en_model": "lm-studio/sauerkraut"
    }
  ],
  "sounds": [
    {
      "ipa": "[nɪçt diː ˈboːnə]",
      "tags": []
    }
  ],
  "phrase_type": "idiom",
  "_antonyms": [
    "sehr",
    "total",
    "überaus"
  ],
  "_meta": {
    "source_hash": "1eaec242acad4d3b",
    "generated_at": "2026-03-09"
  },
  "frequency": 8673
}