{
  "word": "sich den Mund fusselig reden",
  "pos": "phrase",
  "etymology_number": null,
  "senses": [
    {
      "gloss": "immer wieder erfolglos versuchen, jemanden zu etwas zu überreden",
      "gloss_en": "wear someone down with words",
      "tags": [],
      "example_ids": [
        "c501220a95",
        "64a13f4745"
      ],
      "synonyms": [],
      "antonyms": [],
      "gloss_en_model": "lm-studio/sauerkraut"
    }
  ],
  "sounds": [
    {
      "ipa": "[…]",
      "tags": []
    }
  ],
  "phrase_type": "idiom",
  "_synonyms": [
    "sich den Mund fransig reden",
    "sich den Mund in Fransen reden"
  ],
  "_meta": {
    "source_hash": "5cc2718413cc914d",
    "generated_at": "2026-03-09"
  }
}
