{
  "word": "sich etwas hinter die Ohren schreiben",
  "pos": "phrase",
  "etymology_number": null,
  "senses": [
    {
      "gloss": "sich etwas genau, ein für allemal merken",
      "gloss_en": "take to heart",
      "tags": [],
      "example_ids": [
        "a1191335f1"
      ],
      "synonyms": [],
      "antonyms": []
    }
  ],
  "sounds": [
    {
      "ipa": "[…]",
      "tags": []
    }
  ],
  "phrase_type": "idiom",
  "_synonyms": [
    "sich etwas hinter die Löffel schreiben"
  ],
  "_meta": {
    "source_hash": "231e1e9914a8597f",
    "generated_at": "2026-03-09"
  }
}
