{
  "word": "von wannen",
  "pos": "phrase",
  "etymology_number": null,
  "senses": [
    {
      "gloss": "(von) woher",
      "gloss_en": "where from",
      "tags": [
        "outdated"
      ],
      "example_ids": [
        "c843947600",
        "af6b94433c"
      ],
      "synonyms": [],
      "antonyms": []
    }
  ],
  "sounds": [
    {
      "ipa": "[fɔn ˈvanən]",
      "tags": []
    }
  ],
  "phrase_type": "collocation",
  "_antonyms": [
    "von dannen",
    "von hinnen"
  ],
  "_meta": {
    "source_hash": "8d39dc9ff12fdf0b",
    "generated_at": "2026-03-09"
  }
}
