{
  "word": "ausschließlich",
  "pos": "preposition",
  "etymology_number": null,
  "senses": [
    {
      "gloss": "mit Genitiv, veraltet mit Akkusativausschließlich ohne Berücksichtigung von, unter Auslassung/Ausschluss von, mit Ausnahme von",
      "gloss_en": "excluding",
      "tags": [],
      "example_ids": [
        "78dd28db6d",
        "2a073f527c"
      ],
      "synonyms": [],
      "antonyms": [],
      "gloss_en_model": "lm-studio/sauerkraut"
    }
  ],
  "sounds": [
    {
      "ipa": "[ˈaʊ̯sʃliːslɪç]",
      "tags": []
    }
  ],
  "_antonyms": [
    "einschließlich",
    "inklusive",
    "mit"
  ],
  "_synonyms": [
    "ausgenommen",
    "exklusive",
    "ohne"
  ],
  "_meta": {
    "source_hash": "ade42686b6f39dc2",
    "generated_at": "2026-03-09"
  },
  "zipf": 4.22
}