{
  "word": "allerdings",
  "pos": "adverb",
  "etymology_number": null,
  "senses": [
    {
      "gloss": "Kennzeichnung eines Widerspruches oder Einwandes",
      "gloss_en": null,
      "tags": [],
      "example_ids": [
        "25301c7bd6",
        "4ae9fe20d7",
        "ebca11059a",
        "71c0af0892",
        "bd21a5bcb5",
        "b132c07454"
      ],
      "synonyms": [],
      "antonyms": []
    },
    {
      "gloss": "eine verstärkte Bejahung",
      "gloss_en": null,
      "tags": [],
      "example_ids": [
        "d22ee2884f"
      ],
      "synonyms": [],
      "antonyms": []
    }
  ],
  "sounds": [
    {
      "ipa": "[ˈalɐdɪŋs]",
      "tags": []
    },
    {
      "ipa": "[alɐˈdɪŋs]",
      "tags": []
    }
  ],
  "_meta": {
    "source_hash": "20f9489df39a7046",
    "generated_at": "2026-03-01"
  },
  "frequency": 232
}