{
  "word": "besser",
  "pos": "adverb",
  "etymology_number": null,
  "senses": [
    {
      "gloss": "die klügere Alternative wählend",
      "gloss_en": null,
      "tags": [],
      "example_ids": [
        "f517fa2163"
      ],
      "synonyms": [],
      "antonyms": []
    }
  ],
  "sounds": [
    {
      "ipa": "[ˈbɛsɐ]",
      "tags": []
    }
  ],
  "_synonyms": [
    "klugerweise",
    "lieber",
    "vorzugsweise"
  ],
  "_meta": {
    "source_hash": "91114a120085a515",
    "generated_at": "2026-03-06"
  },
  "frequency": 204
}