{
  "word": "fast",
  "pos": "adverb",
  "etymology_number": null,
  "senses": [
    {
      "gloss": "nicht ganz",
      "gloss_en": null,
      "tags": [],
      "example_ids": [
        "f9fd633def",
        "0829aac396",
        "64d15705f3",
        "e30caa000d"
      ],
      "synonyms": [],
      "antonyms": []
    }
  ],
  "sounds": [
    {
      "ipa": "[fast]",
      "tags": []
    }
  ],
  "_meta": {
    "source_hash": "acfdd0a2d029e03f",
    "generated_at": "2026-03-01"
  },
  "frequency": 274
}