{
  "word": "gefüllt",
  "pos": "adjective",
  "etymology_number": null,
  "is_indeclinable": false,
  "comparative": null,
  "superlative": null,
  "umlaut_in_comparison": false,
  "senses": [
    {
      "gloss": "voll gemacht, voll geworden, keinen Platz mehr bietend",
      "gloss_en": null,
      "tags": [],
      "example_ids": [
        "8378d8790a"
      ],
      "synonyms": [],
      "antonyms": []
    }
  ],
  "sounds": [
    {
      "ipa": "[ɡəˈfʏlt]",
      "tags": []
    }
  ],
  "declension_stem": "gefüllt",
  "declension_regular": true,
  "_hyponyms": [
    "benzingefüllt",
    "gasgefüllt",
    "luftgefüllt",
    "rauchgefüllt",
    "wassergefüllt",
    "zementgefüllt"
  ],
  "_meta": {
    "source_hash": "9ac08d1bb7532c0a",
    "generated_at": "2026-03-06"
  },
  "frequency": 5105
}