{
  "word": "laut",
  "pos": "adjective",
  "etymology_number": null,
  "is_indeclinable": false,
  "comparative": "lauter",
  "superlative": "am lautesten",
  "umlaut_in_comparison": false,
  "senses": [
    {
      "gloss": "stark, intensiv; weit zu hören",
      "gloss_en": null,
      "tags": [],
      "example_ids": [
        "13fbfbea29",
        "4e31059734",
        "d896e77aa8",
        "c4f1a25003"
      ],
      "synonyms": [],
      "antonyms": []
    },
    {
      "gloss": "mit Lärm erfüllt; voller störender Geräusche",
      "gloss_en": null,
      "tags": [],
      "example_ids": [
        "945d65d2b6",
        "3d7ca1db6c"
      ],
      "synonyms": [],
      "antonyms": []
    },
    {
      "gloss": "schnell",
      "gloss_en": null,
      "tags": [
        "Erzgebirgisch"
      ],
      "example_ids": [
        "e1f5856630"
      ],
      "synonyms": [],
      "antonyms": []
    }
  ],
  "sounds": [
    {
      "ipa": "[laʊ̯t]",
      "tags": []
    }
  ],
  "declension_stem": "laut",
  "declension_regular": true,
  "expression_ids": [
    "9ab30cee0b"
  ],
  "_derived": [
    "halblaut",
    "lauthals",
    "lautstark",
    "vorlaut",
    "Laut",
    "Lautheit",
    "Lautsprecher",
    "lauten",
    "verlautern"
  ],
  "_antonyms": [
    "leise",
    "ruhig",
    "still"
  ],
  "_synonyms": [
    "forte",
    "geräuschvoll",
    "lärmend",
    "lärmerfüllt"
  ],
  "_meta": {
    "source_hash": "e03f27acb4c2b486",
    "generated_at": "2026-03-06"
  },
  "frequency": 190
}