{
  "word": "momentan",
  "pos": "adjective",
  "etymology_number": null,
  "is_indeclinable": false,
  "comparative": null,
  "superlative": null,
  "umlaut_in_comparison": false,
  "senses": [
    {
      "gloss": "in diesem Moment, jetzt",
      "gloss_en": "current",
      "tags": [],
      "example_ids": [
        "159449057a",
        "6c2ecf6919",
        "2d155ba50d"
      ],
      "synonyms": [],
      "antonyms": [],
      "gloss_en_model": "lm-studio/sauerkraut"
    }
  ],
  "sounds": [
    {
      "ipa": "[momɛnˈtaːn]",
      "tags": []
    }
  ],
  "declension_stem": "momentan",
  "declension_regular": true,
  "_antonyms": [
    "nachher",
    "später",
    "vorher"
  ],
  "_synonyms": [
    "eben",
    "jetzt",
    "gegenwärtig",
    "zurzeit",
    "gerade",
    "heute",
    "heutzutage"
  ],
  "_meta": {
    "source_hash": "9fa3fe551c46101e",
    "generated_at": "2026-03-09"
  },
  "frequency": 2902
}
