{
  "word": "riskant",
  "pos": "adjective",
  "etymology_number": null,
  "is_indeclinable": false,
  "comparative": "riskanter",
  "superlative": "am riskantesten",
  "umlaut_in_comparison": false,
  "senses": [
    {
      "gloss": "mit einem Risiko behaftet/verbunden",
      "gloss_en": null,
      "tags": [],
      "example_ids": [
        "50f6452e6d",
        "fd5663a437",
        "33bcd4ae45",
        "eea9c94551",
        "7b11ab4390",
        "3e1475c5f5",
        "9b64793bf4"
      ],
      "synonyms": [],
      "antonyms": []
    },
    {
      "gloss": "Wirtschaft: bei einem Geschäft oder Anlagen (wie Aktien): mit der Gefahr eines Wertverlustes behaftet",
      "gloss_en": null,
      "tags": [],
      "example_ids": [
        "140fbd73cb",
        "12a75d3d31"
      ],
      "synonyms": [],
      "antonyms": []
    }
  ],
  "sounds": [
    {
      "ipa": "[ʁɪsˈkant]",
      "tags": []
    }
  ],
  "declension_stem": "riskant",
  "declension_regular": true,
  "_hyponyms": [
    "gefährdend",
    "gewagt",
    "ungeschützt",
    "ungesichert"
  ],
  "_antonyms": [
    "sicher",
    "risikolos",
    "verlässlich"
  ],
  "_synonyms": [
    "gewagt",
    "risikoreich",
    "spekulativ"
  ],
  "_meta": {
    "source_hash": "f6629bb6453af1d6",
    "generated_at": "2026-03-06"
  },
  "frequency": 4790
}