{
  "word": "schlecht",
  "pos": "adjective",
  "etymology_number": null,
  "is_indeclinable": false,
  "comparative": "schlechter",
  "superlative": "am schlechtesten",
  "umlaut_in_comparison": false,
  "senses": [
    {
      "gloss": "nicht den Anforderungen oder Erwartungen entsprechend, weil mit Mängeln behaftet",
      "gloss_en": null,
      "tags": [],
      "example_ids": [
        "99c5161e8a",
        "67511142b5",
        "50aba388c5"
      ],
      "synonyms": [],
      "antonyms": []
    },
    {
      "gloss": "nicht hinreichend gut, wenn man es mit dem Zustand vergleicht, der ausreichend oder sogar gut ist",
      "gloss_en": null,
      "tags": [],
      "example_ids": [
        "67511142b5",
        "b79cd70eea",
        "3809cdfc26"
      ],
      "synonyms": [],
      "antonyms": []
    },
    {
      "gloss": "nicht mehr genießbar/anwendbar, etwa bei Lebensmitteln",
      "gloss_en": null,
      "tags": [],
      "example_ids": [
        "f8d88454a4",
        "4755707ba9"
      ],
      "synonyms": [],
      "antonyms": []
    },
    {
      "gloss": "moralisch nicht akzeptabel",
      "gloss_en": null,
      "tags": [],
      "example_ids": [
        "2a96288f0c",
        "97e8358721"
      ],
      "synonyms": [],
      "antonyms": []
    },
    {
      "gloss": "sich unwohl oder krank fühlend",
      "gloss_en": null,
      "tags": [],
      "example_ids": [
        "cfc891ce52"
      ],
      "synonyms": [],
      "antonyms": []
    },
    {
      "gloss": "nicht so, dass es fördert und nützt, sondern so, dass es schadet",
      "gloss_en": null,
      "tags": [],
      "example_ids": [
        "433c4f5dc0",
        "f9cc013413"
      ],
      "synonyms": [],
      "antonyms": []
    },
    {
      "gloss": "nicht so einfach, nur unter großen Mühen",
      "gloss_en": null,
      "tags": [],
      "example_ids": [
        "3599f49e07"
      ],
      "synonyms": [],
      "antonyms": []
    }
  ],
  "sounds": [
    {
      "ipa": "[ʃlɛçt]",
      "tags": []
    }
  ],
  "declension_stem": "schlecht",
  "declension_regular": true,
  "expression_ids": [
    "d17e35f288",
    "3eb0bd8a06",
    "66d2d02380",
    "45543fc0db",
    "d48aff0ae4",
    "44271a455f"
  ],
  "_derived": [
    "Schlechtigkeit",
    "schlechterdings",
    "schlechthin",
    "schlechtweg",
    "verschlechtern"
  ],
  "_hyponyms": [
    "grottenschlecht",
    "sauschlecht"
  ],
  "_meta": {
    "source_hash": "e1505473635d19a4",
    "generated_at": "2026-03-01"
  },
  "frequency": 558
}