{
  "word": "Aktivierung",
  "pos": "noun",
  "etymology_number": null,
  "gender": "F",
  "article": "die",
  "plural_form": "Aktivierungen",
  "gender_rule": {
    "rule_id": "suffix_ung",
    "is_exception": false
  },
  "case_forms": {
    "singular": {
      "nom": "Aktivierung",
      "acc": "Aktivierung",
      "dat": "Aktivierung",
      "gen": "Aktivierung"
    },
    "plural": {
      "nom": "Aktivierungen",
      "acc": "Aktivierungen",
      "dat": "Aktivierungen",
      "gen": "Aktivierungen"
    }
  },
  "senses": [
    {
      "gloss": "die Veranlassung von einer oder mehreren Personen, zu handeln; etwas zum Starten zu bringen",
      "gloss_en": null,
      "tags": [],
      "example_ids": [
        "62696cd35d",
        "04a3e2e8d4",
        "8b0fae9a4f",
        "3de22a6807",
        "12542711fc",
        "dc3666d692",
        "841df395ce",
        "35007b299d",
        "d2acaf10f0"
      ],
      "synonyms": [],
      "antonyms": []
    },
    {
      "gloss": "nach Kauf (oder Eigenerstellung) eines Vermögensgegenstandes dessen Aufnahme in die Bilanz (auf der Aktivseite)",
      "gloss_en": null,
      "tags": [],
      "example_ids": [
        "a2fb7205a9"
      ],
      "synonyms": [],
      "antonyms": []
    },
    {
      "gloss": "Überführung in einen reaktionsbereiten Zustand",
      "gloss_en": null,
      "tags": [],
      "example_ids": [
        "e5cb772bbd"
      ],
      "synonyms": [],
      "antonyms": []
    },
    {
      "gloss": "Zustandsänderung von ruhend zu aktiv",
      "gloss_en": null,
      "tags": [],
      "example_ids": [
        "6c108f2381"
      ],
      "synonyms": [],
      "antonyms": []
    },
    {
      "gloss": "Freischaltung einer Software (nach deren Installation); das Ermöglichen einzelner Features einer Software",
      "gloss_en": null,
      "tags": [],
      "example_ids": [
        "2e167ffd91",
        "2f47521d59",
        "18bbfda29f"
      ],
      "synonyms": [],
      "antonyms": []
    }
  ],
  "sounds": [
    {
      "ipa": "[aktiˈviːʁʊŋ]",
      "tags": []
    }
  ],
  "_derived": [
    "Aktivierungsanalyse",
    "Aktivierungsbefehl",
    "Aktivierungsstärke",
    "aktivierungsfähig",
    "Aktivierungspflicht",
    "Aktivierungsverbot",
    "Aktivierungswahlrecht",
    "Aktivierungsenergie",
    "Aktivierungscode"
  ],
  "_hyponyms": [
    "Überaktivierung"
  ],
  "_antonyms": [
    "Passivierung"
  ],
  "_meta": {
    "source_hash": "accfeecc6aa04241",
    "generated_at": "2026-03-12"
  }
}
