{
  "word": "Aufbau",
  "pos": "noun",
  "etymology_number": null,
  "gender": "M",
  "article": "der",
  "plural_form": "Aufbauten",
  "gender_rule": null,
  "case_forms": {
    "singular": {
      "nom": "Aufbau",
      "acc": "Aufbau",
      "dat": "Aufbau",
      "gen": "Aufbaus"
    },
    "plural": {
      "nom": "Aufbauten",
      "acc": "Aufbauten",
      "dat": "Aufbauten",
      "gen": "Aufbauten"
    }
  },
  "senses": [
    {
      "gloss": "der Vorgang des Aufbauens eines Gebäudes, eines Systems oder einer sonstwie gearteten Struktur",
      "gloss_en": "construction",
      "tags": [
        "no-plural"
      ],
      "example_ids": [
        "c3e5dee173"
      ],
      "synonyms": [],
      "antonyms": [],
      "gloss_en_model": "lm-studio/sauerkraut"
    },
    {
      "gloss": "die Gliederung oder Struktur eines bestehenden Systems (innerer Aufbau)",
      "gloss_en": "structure",
      "tags": [
        "no-plural"
      ],
      "example_ids": [
        "3f6b10cf91"
      ],
      "synonyms": [],
      "antonyms": [],
      "gloss_en_model": "lm-studio/sauerkraut"
    },
    {
      "gloss": "ein Aufsatz oder etwas Aufgesetztes auf ein bestehendes System (oberer Teil eines Gebäudes, einer Karosserie, eines Schiffes)",
      "gloss_en": "structure (construction)",
      "tags": [],
      "example_ids": [
        "2202b55a92",
        "8159912af7"
      ],
      "synonyms": [],
      "antonyms": [],
      "gloss_en_model": "lm-studio/sauerkraut"
    }
  ],
  "sounds": [
    {
      "ipa": "[ˈaʊ̯fˌbaʊ̯]",
      "tags": []
    }
  ],
  "_derived": [
    "Aufbaurennen",
    "Aufbauarbeit",
    "Aufbaugymnasium",
    "Aufbauhelfer",
    "Aufbaumaßnahme",
    "Aufbauprogramm",
    "Aufbaurealschule",
    "Aufbauseminar"
  ],
  "_hyponyms": [
    "Bestandsaufbau",
    "Humusaufbau",
    "Neuaufbau",
    "Umgebungsaufbau",
    "Testumgebungsaufbau",
    "Vermögensaufbau",
    "Versuchsaufbau",
    "Wiederaufbau",
    "Kraftaufbau",
    "Muskelaufbau",
    "Parteiaufbau",
    "Programmaufbau",
    "Schulaufbau",
    "Spielaufbau",
    "Staatsaufbau",
    "Verwaltungsaufbau",
    "Altersaufbau",
    "Atomaufbau",
    "Bildaufbau",
    "Molekularaufbau",
    "Verbindungsaufbau",
    "Wandaufbau",
    "Deckaufbau",
    "Decksaufbau",
    "Kajütsaufbau",
    "Kofferaufbau",
    "Schiffsaufbau"
  ],
  "_antonyms": [
    "Abbau"
  ],
  "_synonyms": [
    "Errichtung",
    "Struktur"
  ],
  "_meta": {
    "source_hash": "73e8658145b8c115",
    "generated_at": "2026-03-09"
  },
  "frequency": 3519
}