{
  "word": "Bezahlkarte",
  "pos": "noun",
  "etymology_number": null,
  "gender": "F",
  "article": "die",
  "plural_form": "Bezahlkarten",
  "gender_rule": null,
  "case_forms": {
    "singular": {
      "nom": "Bezahlkarte",
      "acc": "Bezahlkarte",
      "dat": "Bezahlkarte",
      "gen": "Bezahlkarte"
    },
    "plural": {
      "nom": "Bezahlkarten",
      "acc": "Bezahlkarten",
      "dat": "Bezahlkarten",
      "gen": "Bezahlkarten"
    }
  },
  "senses": [
    {
      "gloss": "bargeldloses Zahlungsmittel, das der Form nach einer Scheckkarte ähnelt",
      "gloss_en": "debit card",
      "tags": [],
      "example_ids": [
        "5db8a0076f"
      ],
      "synonyms": [],
      "antonyms": []
    }
  ],
  "sounds": [
    {
      "ipa": "[bəˈt͡saːlˌkaʁtə]",
      "tags": []
    }
  ],
  "_synonyms": [
    "Zahlkarte",
    "Zahlungskarte"
  ],
  "_meta": {
    "source_hash": "b2997d66c1a0e0bf",
    "generated_at": "2026-03-09"
  },
  "frequency": 6786
}