{
  "word": "Cheftrainer",
  "pos": "noun",
  "etymology_number": null,
  "gender": "M",
  "article": "der",
  "plural_form": "Cheftrainer",
  "gender_rule": null,
  "case_forms": {
    "singular": {
      "nom": "Cheftrainer",
      "acc": "Cheftrainer",
      "dat": "Cheftrainer",
      "gen": "Cheftrainers"
    },
    "plural": {
      "nom": "Cheftrainer",
      "acc": "Cheftrainer",
      "dat": "Cheftrainern",
      "gen": "Cheftrainer"
    }
  },
  "senses": [
    {
      "gloss": "oberster Trainer, der über nachgeordnetes Personal verfügt",
      "gloss_en": null,
      "tags": [],
      "example_ids": [
        "f8a571c781"
      ],
      "synonyms": [],
      "antonyms": []
    }
  ],
  "sounds": [
    {
      "ipa": "[ˈʃɛfˌtʁɛːnɐ]",
      "tags": []
    },
    {
      "ipa": "[ˈʃɛfˌtʁeːnɐ]",
      "tags": []
    },
    {
      "ipa": "[ˈʃɛfˌtʁɛɪ̯nɐ]",
      "tags": []
    }
  ],
  "_meta": {
    "source_hash": "0139ad36ec8e6c1b",
    "generated_at": "2026-03-01"
  },
  "frequency": 4863
}