{
  "word": "Eindruck",
  "pos": "noun",
  "etymology_number": null,
  "gender": "M",
  "article": "der",
  "plural_form": "Eindrücke",
  "gender_rule": null,
  "case_forms": {
    "singular": {
      "nom": "Eindruck",
      "acc": "Eindruck",
      "dat": "Eindruck",
      "gen": "Eindrucks"
    },
    "plural": {
      "nom": "Eindrücke",
      "acc": "Eindrücke",
      "dat": "Eindrücken",
      "gen": "Eindrücke"
    }
  },
  "senses": [
    {
      "gloss": "verbleibende Erinnerung, Vorstellung, die jemand oder etwas hinterlassen hat",
      "gloss_en": "impression",
      "tags": [],
      "example_ids": [
        "325a87d754",
        "46de53d7e3",
        "cf2b867f2c",
        "6807e56fe3",
        "3a28ad7915",
        "23c6b27396"
      ],
      "synonyms": [],
      "antonyms": [],
      "gloss_en_model": "lm-studio/sauerkraut"
    },
    {
      "gloss": "sichtbare Spur",
      "gloss_en": "impression",
      "tags": [],
      "example_ids": [
        "0951d84e0d"
      ],
      "synonyms": [],
      "antonyms": [],
      "gloss_en_model": "lm-studio/sauerkraut"
    }
  ],
  "sounds": [
    {
      "ipa": "[ˈaɪ̯nˌdʁʊk]",
      "tags": []
    }
  ],
  "_derived": [
    "eindrücklich",
    "eindrucksfähig",
    "eindruckslos",
    "eindrucksvoll",
    "Eindruckstelle",
    "beeindrucken"
  ],
  "_hyponyms": [
    "Beeindrucken",
    "Einzeleindruck",
    "Farbeindruck",
    "Gefühlseindruck",
    "Geruchseindruck",
    "Gesamteindruck",
    "Haupteindruck",
    "Judeneindruck",
    "Kriegseindruck",
    "Natureindruck",
    "Pflichteindruck",
    "Reiseeindruck",
    "Sinneseindruck",
    "Totaleindruck"
  ],
  "_meta": {
    "source_hash": "46377be4b021579c",
    "generated_at": "2026-03-09"
  },
  "frequency": 1550
}