{
  "word": "Feigling",
  "pos": "noun",
  "etymology_number": null,
  "gender": "M",
  "article": "der",
  "plural_form": "Feiglinge",
  "gender_rule": {
    "rule_id": "suffix_ling",
    "is_exception": false
  },
  "case_forms": {
    "singular": {
      "nom": "Feigling",
      "acc": "Feigling",
      "dat": "Feigling",
      "gen": "Feiglings"
    },
    "plural": {
      "nom": "Feiglinge",
      "acc": "Feiglinge",
      "dat": "Feiglingen",
      "gen": "Feiglinge"
    }
  },
  "senses": [
    {
      "gloss": "furchtsame, ängstliche, risikoscheue Person",
      "gloss_en": "coward",
      "tags": [],
      "example_ids": [
        "30aed53409",
        "e197ebbc7b",
        "0f8a5a83dd",
        "2e5bc3094f",
        "de2ffd056c"
      ],
      "synonyms": [],
      "antonyms": [],
      "gloss_en_model": "lm-studio/sauerkraut"
    }
  ],
  "sounds": [
    {
      "ipa": "[ˈfaɪ̯klɪŋ]",
      "tags": []
    }
  ],
  "_antonyms": [
    "Draufgänger"
  ],
  "_synonyms": [
    "Angsthase",
    "Bangbüx",
    "Hasenfuß",
    "Memme",
    "Schisser",
    "Trauminet",
    "Hosenkacker",
    "Hosenscheißer"
  ],
  "_meta": {
    "source_hash": "3de8c0680fc84283",
    "generated_at": "2026-03-09"
  },
  "frequency": 2953
}
