{
  "word": "Koks",
  "pos": "noun",
  "etymology_number": null,
  "gender": "M",
  "article": "der",
  "plural_form": "Kokse",
  "gender_rule": null,
  "case_forms": {
    "singular": {
      "nom": "Koks",
      "acc": "Koks",
      "dat": "Koks",
      "gen": "Koks"
    },
    "plural": {
      "nom": "Kokse",
      "acc": "Kokse",
      "dat": "Koksen",
      "gen": "Kokse"
    }
  },
  "senses": [
    {
      "gloss": "steifer Hut",
      "gloss_en": "stiff hat",
      "tags": [
        "archaic",
        "colloquial"
      ],
      "example_ids": [
        "b9c7abb0ca"
      ],
      "synonyms": [],
      "antonyms": [],
      "gloss_en_model": "lm-studio/sauerkraut"
    }
  ],
  "sounds": [
    {
      "ipa": "[koːks]",
      "tags": []
    }
  ],
  "_synonyms": [
    "Melone"
  ],
  "_meta": {
    "source_hash": "1040ecb1b5f0baf0",
    "generated_at": "2026-03-09"
  },
  "frequency": 6334
}
