{
  "word": "Nachricht",
  "pos": "noun",
  "etymology_number": null,
  "gender": "F",
  "article": "die",
  "plural_form": "Nachrichten",
  "gender_rule": null,
  "case_forms": {
    "singular": {
      "nom": "Nachricht",
      "acc": "Nachricht",
      "dat": "Nachricht",
      "gen": "Nachricht"
    },
    "plural": {
      "nom": "Nachrichten",
      "acc": "Nachrichten",
      "dat": "Nachrichten",
      "gen": "Nachrichten"
    }
  },
  "senses": [
    {
      "gloss": "Mitteilung über den Sachverhalt von wichtigen Neuigkeiten",
      "gloss_en": "message",
      "tags": [],
      "example_ids": [
        "f18a87bbe3",
        "f904d99367",
        "fc57b4a9cd",
        "f61f44a692",
        "9ed27779c8",
        "7b0c8d53ad"
      ],
      "synonyms": [],
      "antonyms": []
    },
    {
      "gloss": "eine schriftliche oder hinterlassene Mitteilung von Informationen",
      "gloss_en": "message",
      "tags": [],
      "example_ids": [
        "99bc0ab118"
      ],
      "synonyms": [],
      "antonyms": []
    },
    {
      "gloss": "Sendung, in der aktuelle Ereignisse und Neuigkeiten vermittelt werden",
      "gloss_en": "news",
      "tags": [
        "plural"
      ],
      "example_ids": [
        "754afe8de6",
        "ab9777bdbc",
        "e0e266514f"
      ],
      "synonyms": [],
      "antonyms": []
    },
    {
      "gloss": "journalistische Textsorte; relativ kurzer Text mit der überwiegenden/ausschließlichen Funktion, Informationen weiterzugeben",
      "gloss_en": "news report",
      "tags": [],
      "example_ids": [
        "bc6f4215c1",
        "9e5453338a",
        "ce0e95e879"
      ],
      "synonyms": [],
      "antonyms": []
    }
  ],
  "sounds": [
    {
      "ipa": "[ˈnaːxˌʁɪçt]",
      "tags": []
    }
  ],
  "_derived": [
    "nachrichtlich",
    "Nachrichtenagentur",
    "Nachrichtendienst",
    "Nachrichtenkanal",
    "Nachrichtenmagazin",
    "Nachrichtenmarkt",
    "Nachrichtenpolitik",
    "Nachrichtenportal",
    "Nachrichtensatellit",
    "Nachrichtensendung",
    "Nachrichtensperre",
    "Nachrichtensprache",
    "Nachrichtensprecher",
    "Nachrichtensystem",
    "Nachrichtentechnik",
    "Nachrichtenübermittlung",
    "Nachrichtenverbindung",
    "Nachrichtenwert",
    "Nachrichtenwesen"
  ],
  "_hyponyms": [
    "Auslandsnachricht",
    "Erfolgsnachricht",
    "Falschnachricht",
    "Inlandsnachricht",
    "Kulturnachricht",
    "Morgennachricht",
    "Schreckensnachricht",
    "Siegesnachricht",
    "Sperrnachricht",
    "Sportnachricht",
    "Tatarennachricht",
    "Todesnachricht",
    "Wirtschaftsnachricht",
    "Chatnachricht",
    "E-Mail-Nachricht",
    "Kurznachricht",
    "Sprachnachricht",
    "Textnachricht",
    "Videonachricht",
    "Abendnachrichten",
    "Kurznachrichten",
    "Morgennachrichten",
    "Originalnachrichten",
    "Regionalnachrichten",
    "Spätnachrichten",
    "Sportnachrichten",
    "Tagesnachrichten",
    "harte Nachricht",
    "hard news",
    "weiche Nachricht",
    "soft news",
    "Fernsehnachricht",
    "Meldung",
    "Radionachricht",
    "Zeitungsnachricht"
  ],
  "_synonyms": [
    "Botschaft",
    "Kunde",
    "News"
  ],
  "_meta": {
    "source_hash": "814d733228dec0fe",
    "generated_at": "2026-03-09"
  },
  "frequency": 773
}