{
  "word": "Schreibe",
  "pos": "noun",
  "etymology_number": null,
  "gender": "F",
  "article": "die",
  "plural_form": "Schreiben",
  "gender_rule": null,
  "case_forms": {
    "singular": {
      "nom": "Schreibe",
      "acc": "Schreibe",
      "dat": "Schreibe",
      "gen": "Schreibe"
    },
    "plural": {
      "nom": "Schreiben",
      "acc": "Schreiben",
      "dat": "Schreiben",
      "gen": "Schreiben"
    }
  },
  "senses": [
    {
      "gloss": "Art, Stil sich schriftlich auszudrücken",
      "gloss_en": "style",
      "tags": [
        "colloquial"
      ],
      "example_ids": [
        "9dd9e34b8f",
        "65e18580d8"
      ],
      "synonyms": [],
      "antonyms": [],
      "gloss_en_model": "lm-studio/sauerkraut"
    },
    {
      "gloss": "geschriebene Sprache",
      "gloss_en": "writing",
      "tags": [
        "colloquial"
      ],
      "example_ids": [],
      "synonyms": [],
      "antonyms": [],
      "gloss_en_model": "lm-studio/sauerkraut"
    },
    {
      "gloss": "Schreibgerät",
      "gloss_en": "pen",
      "tags": [
        "colloquial",
        "outdated"
      ],
      "example_ids": [],
      "synonyms": [],
      "antonyms": [],
      "gloss_en_model": "lm-studio/sauerkraut"
    }
  ],
  "sounds": [
    {
      "ipa": "[ˈʃʁaɪ̯bə]",
      "tags": []
    }
  ],
  "expression_ids": [
    "7fef86c418"
  ],
  "_synonyms": [
    "Schreibweise",
    "Schreibstil",
    "Schreibung",
    "Geschriebenes"
  ],
  "_meta": {
    "source_hash": "751d9f2700775a2d",
    "generated_at": "2026-03-09"
  },
  "frequency": 2362
}
