{
  "word": "Schwarz",
  "pos": "noun",
  "etymology_number": null,
  "gender": null,
  "article": null,
  "plural_form": null,
  "gender_rule": null,
  "case_forms": {
    "singular": {
      "nom": "Schwarz",
      "acc": "Schwarz",
      "dat": "Schwarz",
      "gen": "Schwarz"
    },
    "plural": {
      "nom": null,
      "acc": null,
      "dat": null,
      "gen": null
    }
  },
  "senses": [
    {
      "gloss": "in den Spielen Schach, Dame, Mühle und Go der Spieler mit den schwarzen Spielsteinen",
      "gloss_en": null,
      "tags": [],
      "example_ids": [
        "fac6c3a5e4"
      ],
      "synonyms": [],
      "antonyms": []
    },
    {
      "gloss": "Farbe, Farbton der Bekleidung; im westlichen Kulturkreis ist Schwarz die Farbe der Trauer und des Todes, Farbe der Trauerkleidung",
      "gloss_en": null,
      "tags": [],
      "example_ids": [
        "335abe4079",
        "013e4ff6e2"
      ],
      "synonyms": [],
      "antonyms": []
    }
  ],
  "sounds": [
    {
      "ipa": "[ʃvaʁt͡s]",
      "tags": []
    }
  ],
  "_antonyms": [
    "Weiß"
  ],
  "_meta": {
    "source_hash": "c541df3e3e1e2d89",
    "generated_at": "2026-03-06"
  },
  "frequency": 1912
}