{
  "word": "Täterin",
  "pos": "noun",
  "etymology_number": null,
  "gender": "F",
  "article": "die",
  "plural_form": "Täterinnen",
  "gender_rule": null,
  "case_forms": {
    "singular": {
      "nom": "Täterin",
      "acc": "Täterin",
      "dat": "Täterin",
      "gen": "Täterin"
    },
    "plural": {
      "nom": "Täterinnen",
      "acc": "Täterinnen",
      "dat": "Täterinnen",
      "gen": "Täterinnen"
    }
  },
  "senses": [
    {
      "gloss": "weibliche Person, die sich etwas zuschulden kommen lassen hat",
      "gloss_en": "female offender",
      "tags": [],
      "example_ids": [
        "0d13664ebb",
        "0fe90f9325"
      ],
      "synonyms": [],
      "antonyms": [],
      "gloss_en_model": "lm-studio/sauerkraut"
    }
  ],
  "sounds": [
    {
      "ipa": "[ˈtɛːtəʁɪn]",
      "tags": []
    }
  ],
  "_hyponyms": [
    "Ersttäterin",
    "Missetäterin",
    "Rückfalltäterin",
    "Schreibtischtäterin",
    "Serientäterin",
    "Straftäterin",
    "Triebtäterin",
    "Übeltäterin",
    "Wiederholungstäterin"
  ],
  "_gender_counterpart": "Täter",
  "_meta": {
    "source_hash": "1121a30a6aa60d43",
    "generated_at": "2026-03-09"
  },
  "zipf": 2.92
}