{
  "word": "Umkreis",
  "pos": "noun",
  "etymology_number": null,
  "gender": "M",
  "article": "der",
  "plural_form": "Umkreise",
  "gender_rule": null,
  "case_forms": {
    "singular": {
      "nom": "Umkreis",
      "acc": "Umkreis",
      "dat": "Umkreis",
      "gen": "Umkreises"
    },
    "plural": {
      "nom": "Umkreise",
      "acc": "Umkreise",
      "dat": "Umkreisen",
      "gen": "Umkreise"
    }
  },
  "senses": [
    {
      "gloss": "das umgebende Gebiet, die Umgebung",
      "gloss_en": "area (surrounding)",
      "tags": [],
      "example_ids": [
        "2de56cdc1e",
        "6320c6bb57",
        "ab15cb999e",
        "30a903a180"
      ],
      "synonyms": [],
      "antonyms": [],
      "gloss_en_model": "lm-studio/sauerkraut"
    },
    {
      "gloss": "Kreis, der durch alle Eckpunkte eines Polygons verläuft",
      "gloss_en": "circumcircle",
      "tags": [
        "geometry"
      ],
      "example_ids": [
        "53fd088574"
      ],
      "synonyms": [],
      "antonyms": [],
      "gloss_en_model": "lm-studio/sauerkraut"
    }
  ],
  "sounds": [
    {
      "ipa": "[ˈʊmˌkʁaɪ̯s]",
      "tags": []
    }
  ],
  "_derived": [
    "Umkreissuche"
  ],
  "_antonyms": [
    "Inkreis"
  ],
  "_meta": {
    "source_hash": "e969c299620bc579",
    "generated_at": "2026-03-09"
  },
  "frequency": 4871
}