{
  "word": "Unfallstelle",
  "pos": "noun",
  "etymology_number": null,
  "gender": "F",
  "article": "die",
  "plural_form": "Unfallstellen",
  "gender_rule": null,
  "case_forms": {
    "singular": {
      "nom": "Unfallstelle",
      "acc": "Unfallstelle",
      "dat": "Unfallstelle",
      "gen": "Unfallstelle"
    },
    "plural": {
      "nom": "Unfallstellen",
      "acc": "Unfallstellen",
      "dat": "Unfallstellen",
      "gen": "Unfallstellen"
    }
  },
  "senses": [
    {
      "gloss": "lokalisierbarer Platz eines Vorfalls, bei dem Sachen oder Menschen zu schaden kommen",
      "gloss_en": null,
      "tags": [],
      "example_ids": [
        "d558bb9339",
        "b64a22368d",
        "d7df7697c5"
      ],
      "synonyms": [],
      "antonyms": []
    }
  ],
  "sounds": [
    {
      "ipa": "[ˈʊnfalˌʃtɛlə]",
      "tags": []
    }
  ],
  "_synonyms": [
    "Unfallort"
  ],
  "_meta": {
    "source_hash": "7bb33692d1cfd6e4",
    "generated_at": "2026-03-06"
  },
  "frequency": 3943
}