{
  "word": "Wahlsieg",
  "pos": "noun",
  "etymology_number": null,
  "gender": "M",
  "article": "der",
  "plural_form": "Wahlsiege",
  "gender_rule": null,
  "case_forms": {
    "singular": {
      "nom": "Wahlsieg",
      "acc": "Wahlsieg",
      "dat": "Wahlsieg",
      "gen": "Wahlsieges"
    },
    "plural": {
      "nom": "Wahlsiege",
      "acc": "Wahlsiege",
      "dat": "Wahlsiegen",
      "gen": "Wahlsiege"
    }
  },
  "senses": [
    {
      "gloss": "das Gewinnen bei einer Wahl",
      "gloss_en": "election victory",
      "tags": [],
      "example_ids": [
        "d49b3e35af",
        "3c030bcc5b",
        "d7bc6e5bfe",
        "0602e9f7fa",
        "e20f316f2f",
        "c07772f24d"
      ],
      "synonyms": [],
      "antonyms": [],
      "gloss_en_model": "lm-studio/sauerkraut"
    }
  ],
  "sounds": [
    {
      "ipa": "[ˈvaːlˌziːk]",
      "tags": []
    }
  ],
  "_antonyms": [
    "Wahlniederlage"
  ],
  "_synonyms": [
    "Wahlgewinn"
  ],
  "_meta": {
    "source_hash": "f6a89c694b2a4b23",
    "generated_at": "2026-03-09"
  },
  "frequency": 7509
}