{
  "word": "eignen",
  "pos": "verb",
  "etymology_number": null,
  "auxiliary": "haben",
  "separable": false,
  "prefix": null,
  "reflexive": "optional",
  "conjugation_class": "weak",
  "stems": {
    "present": "eign"
  },
  "past_participle": "geeignet",
  "senses": [
    {
      "gloss": "für einen Einsatz, eine Funktion benötigte Eigenschaften oder Fähigkeiten besitzen",
      "gloss_en": "suitable",
      "tags": [
        "reflexive"
      ],
      "example_ids": [
        "a48f0c78a5",
        "e9c8327f4f"
      ],
      "synonyms": [],
      "antonyms": [],
      "gloss_en_model": "lm-studio/sauerkraut"
    },
    {
      "gloss": "einer Person, einer Sache als Merkmal zugehören",
      "gloss_en": "belong",
      "tags": [
        "literary"
      ],
      "example_ids": [
        "d746debe47"
      ],
      "synonyms": [],
      "antonyms": [],
      "gloss_en_model": "lm-studio/sauerkraut"
    }
  ],
  "sounds": [
    {
      "ipa": "[ˈaɪ̯ɡnən]",
      "tags": []
    }
  ],
  "_derived": [
    "Eignen",
    "eignend",
    "geeignet",
    "Eigner",
    "Eignung",
    "aneignen",
    "enteignen",
    "übereignen",
    "zueignen"
  ],
  "_synonyms": [
    "geeignet",
    "taugen",
    "anhängen",
    "innewohnen",
    "zugehören",
    "eigen"
  ],
  "_meta": {
    "source_hash": "0887c5446befa1e8",
    "generated_at": "2026-03-09"
  },
  "frequency": 6380
}