{
  "word": "gefrieren",
  "pos": "verb",
  "etymology_number": null,
  "auxiliary": "sein",
  "separable": false,
  "prefix": null,
  "reflexive": "none",
  "senses": [
    {
      "gloss": "durch Kälteeinwirkung fest und hart werden, zu Eis erstarren",
      "gloss_en": null,
      "tags": [
        "intransitive"
      ],
      "example_ids": [],
      "synonyms": [],
      "antonyms": []
    },
    {
      "gloss": "Lebensmittel durch Kühlmittel einfrieren oder tiefgefrieren, um sie haltbar zu machen",
      "gloss_en": null,
      "tags": [
        "transitive"
      ],
      "example_ids": [],
      "synonyms": [],
      "antonyms": []
    }
  ],
  "sounds": [
    {
      "ipa": "[ɡəˈfʁiːʁən]",
      "tags": []
    }
  ],
  "conjugation_class": "strong",
  "stems": {
    "present": "gefrier",
    "past": "gefror",
    "subj2": "gefrör"
  },
  "past_participle": "gefroren",
  "_derived": [
    "gefrierstabil",
    "Gefrieren",
    "gefrierend",
    "gefroren",
    "Gefrieranlage",
    "Gefrierapparat",
    "Gefrierbehandlung",
    "Gefrierbeutel",
    "Gefrierbrand",
    "Gefrierchirurgie",
    "Gefrierfach",
    "Gefrierfleisch",
    "Gefriergemüse",
    "Gefriergeräte",
    "Gefriergut",
    "Gefrierkette",
    "Gefrierlagerung",
    "Gefriermaschine",
    "Gefrierobst",
    "Gefrierpunkt",
    "Gefrierraum",
    "Gefriersalz",
    "Gefrierschaden",
    "Gefrierschiff",
    "Gefrierschnitt",
    "Gefrierschrank",
    "Gefrierschutz",
    "Gefriertemperatur",
    "Gefriertruhe",
    "Gefriertunnel",
    "Gefrierverfahren",
    "Gefrornis",
    "eingefrieren",
    "gefriertrocknen",
    "schockgefrieren",
    "tiefgefrieren"
  ],
  "_hyponyms": [
    "festfrieren",
    "überfrieren",
    "zufrieren",
    "schockgefrieren",
    "tiefgefrieren",
    "tiefkühlen"
  ],
  "_antonyms": [
    "schmelzen",
    "tauen",
    "auftauen"
  ],
  "_synonyms": [
    "durchfrieren",
    "einfrieren",
    "einfrosten"
  ],
  "_meta": {
    "source_hash": "4303ac1844ba994a",
    "generated_at": "2026-03-19"
  }
}
