{
  "word": "hervorbringen",
  "pos": "verb",
  "etymology_number": null,
  "auxiliary": "haben",
  "separable": true,
  "prefix": "hervor",
  "reflexive": "none",
  "senses": [
    {
      "gloss": "etwas herausholen",
      "gloss_en": null,
      "tags": [],
      "example_ids": [
        "03fd8b5a70"
      ],
      "synonyms": [],
      "antonyms": []
    },
    {
      "gloss": "etwas mündlich sagen, aussprechen",
      "gloss_en": null,
      "tags": [],
      "example_ids": [
        "1463e7975b"
      ],
      "synonyms": [],
      "antonyms": []
    },
    {
      "gloss": "etwas anfertigen, zustande bringen",
      "gloss_en": null,
      "tags": [],
      "example_ids": [
        "e93cc1b4e1",
        "a551763610",
        "8f366ba96f",
        "88b0794569"
      ],
      "synonyms": [],
      "antonyms": []
    }
  ],
  "sounds": [
    {
      "ipa": "[hɛɐ̯ˈfoːɐ̯ˌbʁɪŋən]",
      "tags": []
    }
  ],
  "conjugation_class": "mixed",
  "stems": {
    "present": "bring",
    "past": "brach",
    "subj2": "bräch"
  },
  "past_participle": "hervorgebracht",
  "_derived": [
    "Hervorbringung"
  ],
  "_synonyms": [
    "herausbringen",
    "hervorholen",
    "sagen",
    "sprechen",
    "erschaffen",
    "erzeugen",
    "herstellen",
    "leisten",
    "machen",
    "produzieren",
    "schaffen"
  ],
  "_meta": {
    "source_hash": "710578ed17b89dbd",
    "generated_at": "2026-03-19"
  }
}
