{
  "word": "pilgern",
  "pos": "verb",
  "etymology_number": null,
  "auxiliary": "sein",
  "separable": false,
  "prefix": null,
  "reflexive": "none",
  "senses": [
    {
      "gloss": "aus religiösen Gründen eine Reise unternehmen",
      "gloss_en": null,
      "tags": [],
      "example_ids": [
        "8052890cd1",
        "df9829de5a"
      ],
      "synonyms": [],
      "antonyms": []
    },
    {
      "gloss": "irgendwohin wandern, gehen",
      "gloss_en": null,
      "tags": [
        "colloquial"
      ],
      "example_ids": [
        "6b8e23beb7",
        "727de25b59",
        "207a141202"
      ],
      "synonyms": [],
      "antonyms": []
    }
  ],
  "sounds": [
    {
      "ipa": "[ˈpɪlɡɐn]",
      "tags": []
    }
  ],
  "conjugation_class": "weak",
  "stems": {
    "present": "pilger",
    "past": ""
  },
  "past_participle": "gepilgert",
  "_derived": [
    "Pilgerfahrt",
    "Pilgerflasche",
    "Pilgergewand",
    "Pilgerhut",
    "Pilgerkirche",
    "Pilgerkleid",
    "Pilgermantel",
    "Pilgermuschel",
    "Pilgerort",
    "Pilgerpass",
    "Pilgerreise",
    "Pilgerschaft",
    "Pilgerschar",
    "Pilgersfrau",
    "Pilgersmann",
    "Pilgerstab",
    "Pilgerstätte",
    "Pilgerstadt",
    "Pilgerwanderer",
    "Pilgerweg",
    "Pilgerzug"
  ],
  "_synonyms": [
    "wallfahren"
  ],
  "_meta": {
    "source_hash": "938ce216f81240f6",
    "generated_at": "2026-03-19"
  }
}
