{
  "word": "stressen",
  "pos": "verb",
  "etymology_number": null,
  "auxiliary": "haben",
  "separable": false,
  "prefix": null,
  "reflexive": "none",
  "senses": [
    {
      "gloss": "unter Druck setzen; jemanden psychisch belasten; Stress auslösen",
      "gloss_en": null,
      "tags": [
        "colloquial",
        "transitive"
      ],
      "example_ids": [],
      "synonyms": [],
      "antonyms": []
    }
  ],
  "sounds": [
    {
      "ipa": "[ˈʃtʁɛsn̩]",
      "tags": []
    }
  ],
  "conjugation_class": "weak",
  "stems": {
    "present": "stress",
    "past": ""
  },
  "past_participle": "gestresst",
  "_derived": [
    "gestresst",
    "Stressen",
    "stressend",
    "rumstressen"
  ],
  "_synonyms": [
    "anstrengen",
    "aufreiben",
    "schlauchen"
  ],
  "_meta": {
    "source_hash": "365b08b5ab6565a1",
    "generated_at": "2026-03-19"
  }
}
