{
  "word": "überfahren",
  "pos": "verb",
  "etymology_number": null,
  "auxiliary": "both",
  "separable": true,
  "prefix": "über",
  "reflexive": "none",
  "conjugation_class": "strong",
  "stems": {
    "present": "fahr",
    "past": "fuhr",
    "present_du_er": "fähr",
    "subj2": "führ",
    "imperative_du": "fahre"
  },
  "past_participle": "übergefahren",
  "senses": [
    {
      "gloss": "mit einem Wasserfahrzeug von einem Ufer zum anderen fahren",
      "gloss_en": null,
      "tags": [],
      "example_ids": [
        "332af2eb37",
        "2012705574"
      ],
      "synonyms": [],
      "antonyms": []
    }
  ],
  "sounds": [
    {
      "ipa": "[ˈyːbɐˌfaːʁən]",
      "tags": []
    }
  ],
  "_derived": [
    "Überfahren",
    "überfahrend",
    "übergefahren",
    "Überfuhr",
    "Überfahrt"
  ],
  "_synonyms": [
    "übersetzen"
  ],
  "_meta": {
    "source_hash": "329d85c1606f8895",
    "generated_at": "2026-03-06"
  },
  "frequency": 5132
}